setup.py
lavda/__init__.py
lavda.egg-info/PKG-INFO
lavda.egg-info/SOURCES.txt
lavda.egg-info/dependency_links.txt
lavda.egg-info/requires.txt
lavda.egg-info/top_level.txt
lavda.egg-info/zip-safe
lavda/analysis/__init__.py
lavda/analysis/common.py
lavda/analysis/da_clean/__init__.py
lavda/analysis/da_clean/ads_spam.py
lavda/analysis/da_clean/all_text_spam.py
lavda/analysis/da_clean/clean_interface.py
lavda/analysis/da_clean/df_distinct.py
lavda/analysis/da_clean/ec_spam.py
lavda/analysis/da_clean/navy_judgment.py
lavda/analysis/da_clean/other_spam.py
lavda/analysis/da_clean/unkeyword_spam.py
lavda/analysis/da_clean/water_spam.py
lavda/analysis/da_extract/__init__.py
lavda/analysis/da_extract/age_format.py
lavda/analysis/da_extract/area.py
lavda/analysis/da_extract/city_rank.py
lavda/analysis/da_extract/datetime_format.py
lavda/analysis/da_extract/gender_format.py
lavda/analysis/da_extract/hastag_extract.py
lavda/analysis/da_extract/number_format.py
lavda/analysis/da_extract/text_format.py
lavda/analysis/da_extract/user_tag.py
lavda/analysis/da_filter/__init__.py
lavda/analysis/da_filter/clean_filter.py
lavda/analysis/da_filter/column_match_filter.py
lavda/analysis/da_filter/filter_interface.py
lavda/analysis/da_pre/__init__.py
lavda/analysis/da_pre/create_data_index.py
lavda/analysis/da_pre/df_format_data.py
lavda/analysis/da_save/__init__.py
lavda/analysis/da_save/more_sheet_save.py
lavda/analysis/da_save/spark_writer.py
lavda/analysis/da_statis/__init__.py
lavda/analysis/da_statis/da_qa_class.py
lavda/analysis/da_tag/Filed_Services.py
lavda/analysis/da_tag/__init__.py
lavda/analysis/da_tag/diatance_tag.py
lavda/analysis/da_tag/label_core.py
lavda/analysis/da_tag/label_dict.py
lavda/analysis/da_tag/label_extract.py
lavda/analysis/da_tag/label_keyword.py
lavda/analysis/da_tag/label_main.py
lavda/analysis/da_tag/label_model.py
lavda/analysis/da_tag/label_util.py
lavda/analysis/da_tag/label_verify.py
lavda/analysis/da_tag/mapping_models.py
lavda/analysis/da_tag/split_tag.py
lavda/analysis/da_tag/tag.py
lavda/analysis/da_tag/tag_config.py
lavda/analysis/da_tag/tag_deal.py
lavda/analysis/da_tag/tag_dict.py
