Metadata-Version: 1.1
Name: lavda
Version: 0.0.5
Summary: data process and analysis
Home-page: UNKNOWN
Author: lavector data_analysis
Author-email: hao.jia@lavector.com
License: UNKNOWN
Platform: UNKNOWN
Classifier: Environment :: Web Environment
Classifier: Intended Audience :: Developers
Classifier: License :: OSI Approved :: MIT License
Classifier: Operating System :: MacOS
Classifier: Operating System :: Microsoft
Classifier: Operating System :: POSIX
Classifier: Operating System :: Unix
Classifier: Programming Language :: Python :: 3.8
Classifier: Programming Language :: Python :: 3.5
Classifier: Programming Language :: Python :: 3.6
